allure.py
allure_commons/__init__.py
allure_commons/_allure.py
allure_commons/_core.py
allure_commons/_hooks.py
allure_commons/lifecycle.py
allure_commons/logger.py
allure_commons/mapping.py
allure_commons/model2.py
allure_commons/reporter.py
allure_commons/types.py
allure_commons/utils.py
allure_python_commons-2.13.5.dist-info/METADATA
allure_python_commons-2.13.5.dist-info/WHEEL
allure_python_commons-2.13.5.dist-info/top_level.txt
allure_python_commons-2.13.5.dist-info/RECORD
