Metadata-Version: 2.1
Name: allure-python-commons
Version: 2.13.5
Summary: ('Contains the API for end users as well as helper functions and classes to build Allure adapters for Python test frameworks',)
Home-page: https://allurereport.org/
Author: Qameta Software Inc., Stanislav Seliverstov
Author-email: sseliverstov@qameta.io
License: Apache-2.0
Project-URL: Source, https://github.com/allure-framework/allure-python
Keywords: allure reporting report-engine
Classifier: Development Status :: 5 - Production/Stable
Classifier: Intended Audience :: Developers
Classifier: License :: OSI Approved :: Apache Software License
Classifier: Topic :: Software Development :: Quality Assurance
Classifier: Topic :: Software Development :: Testing
Classifier: Programming Language :: Python :: 3
Classifier: Programming Language :: Python :: 3 :: Only
Classifier: Programming Language :: Python :: 3.7
Classifier: Programming Language :: Python :: 3.8
Classifier: Programming Language :: Python :: 3.9
Classifier: Programming Language :: Python :: 3.10
Classifier: Programming Language :: Python :: 3.11
Classifier: Programming Language :: Python :: 3.12
Requires-Python: >=3.6
Requires-Dist: attrs>=16.0.0
Requires-Dist: pluggy>=0.4.0
